LICENSE
MANIFEST.in
README.rst
setup.py
django_onesky.egg-info/PKG-INFO
django_onesky.egg-info/SOURCES.txt
django_onesky.egg-info/dependency_links.txt
django_onesky.egg-info/top_level.txt
onesky/__init__.py
onesky/inline.py
onesky/tests.py
onesky/templatetags/__init__.py
onesky/templatetags/onesky/__init__.py
onesky/templatetags/onesky/inline.py