Metadata-Version: 1.1
Name: django-onesky
Version: 0.2
Summary: OneSky inline translation library for Django
Home-page: http://github.com/onesky/django-onesky/
Author: Chris Lam
Author-email: chris@oneyskyapp.com
License: MIT License
Platform: UNKNOWN
Classifier: Environment :: Web Environment
Classifier: Framework :: Django
Classifier: Intended Audience :: Developers
Classifier: License :: OSI Approved :: MIT License
Classifier: Operating System :: OS Independent
Classifier: Programming Language :: Python
Classifier: Topic :: Text Processing :: Linguistic
Classifier: Topic :: Utilities
